ltop/__init__.py
ltop/filter_ltop_logs.py
ltop/log_retention.py
ltop/ltop.py
ltop-0.2.dist-info/METADATA
ltop-0.2.dist-info/WHEEL
ltop-0.2.dist-info/entry_points.txt
ltop-0.2.dist-info/top_level.txt
ltop-0.2.dist-info/RECORD
